{
  "parent": "minecraft:recipes/root",
  "rewards": {
    "recipes": [
      "usefulguns:glass_bullet"
    ]
  },
  "criteria": {
    "": {
      "trigger": "minecraft:inventory_changed",
      "conditions": {
        "items": [
          {
            "items": [
              "minecraft:air"
            ]
          }
        ]
      }
    },
    "has_the_recipe": {
      "trigger": "minecraft:recipe_unlocked",
      "conditions": {
        "recipe": "usefulguns:glass_bullet"
      }
    }
  },
  "requirements": [
    [
      "",
      "has_the_recipe"
    ]
  ]
}