{
  "parent": "minecraft:item/handheld",
  "textures": {
    "layer0": "usefulguns:items/iron_mining_bullet"
  },
  "overrides": [
    {
      "predicate": {
        "usefulguns:enchantment_id": 0.0
      },
      "model": "usefulguns:item/iron_mining_bullet_0"
    },
    {
      "predicate": {
        "usefulguns:enchantment_id": 0.1
      },
      "model": "usefulguns:item/iron_mining_bullet_1"
    },
    {
      "predicate": {
        "usefulguns:enchantment_id": 0.2
      },
      "model": "usefulguns:item/iron_mining_bullet_2"
    },
    {
      "predicate": {
        "usefulguns:enchantment_id": 0.3
      },
      "model": "usefulguns:item/iron_mining_bullet_3"
    },
    {
      "predicate": {
        "usefulguns:enchantment_id": 0.4
      },
      "model": "usefulguns:item/iron_mining_bullet_4"
    }
  ]
}